rhinox/__init__.py
rhinox/client.py
rhinox/headers.py
rhinox/urls.py
rhinox/endpoints/__init__.py
rhinox/endpoints/menu.py
rhinox/models/__init__.py
rhinox/models/menu.py
rhinox/models/no_extra.py
rhinox-0.0.4.dist-info/LICENSE
rhinox-0.0.4.dist-info/METADATA
rhinox-0.0.4.dist-info/WHEEL
rhinox-0.0.4.dist-info/top_level.txt
rhinox-0.0.4.dist-info/RECORD
