Metadata-Version: 2.1
Name: rhinox
Version: 0.0.4
Summary: http://api.rhinox.io/api/documentation
Home-page: https://pypi.org/project/rhinox/
Author: Alejo Prieto Dávalos
Author-email: alejoprietodavalos@gmail.com
Project-URL: Source, https://github.com/AlejoPrietoDavalos/rhinox/
Requires-Python: >=3.11
License-File: LICENSE
Requires-Dist: requests>=2.32
Requires-Dist: pydantic>=2.8
